duplicateticketsearch/__init__.py
duplicateticketsearch/htdocs/css/tracDupeSearch.css
duplicateticketsearch/htdocs/js/tracDupeSearch.js
TracDuplicateTicketSearch-1.0.5.dist-info/COPYING
TracDuplicateTicketSearch-1.0.5.dist-info/METADATA
TracDuplicateTicketSearch-1.0.5.dist-info/WHEEL
TracDuplicateTicketSearch-1.0.5.dist-info/entry_points.txt
TracDuplicateTicketSearch-1.0.5.dist-info/top_level.txt
TracDuplicateTicketSearch-1.0.5.dist-info/RECORD
