Metadata-Version: 2.1
Name: TracDuplicateTicketSearch
Version: 1.0.5
Summary: Adds XMLRPC-based check from ticket entry page for potential duplicate tickets.
Home-page: https://trac-hacks.org/wiki/DuplicateTicketSearchPlugin
Author: gregmac
Author-email: UNKNOWN
License: BSD
Keywords: trac duplicate ticket search plugin
Platform: UNKNOWN
Classifier: Framework :: Trac
Requires-Dist: TracXMLRPC
Requires-Dist: Trac
